nexus/__init__.py
nexus/main.py
nexus/version.py
nexus/analysis/__init__.py
nexus/analysis/analyzer_factory.py
nexus/analysis/strategy_factory.py
nexus/analysis/analyzers/average_cluster_size_analyzer.py
nexus/analysis/analyzers/base_analyzer.py
nexus/analysis/analyzers/cluster_size_distribution_analyzer.py
nexus/analysis/analyzers/concentration_analyzer.py
nexus/analysis/analyzers/correlation_length_analyzer.py
nexus/analysis/analyzers/gyration_radius_analyzer.py
nexus/analysis/analyzers/largest_cluster_size_analyzer.py
nexus/analysis/analyzers/order_parameter_analyzer.py
nexus/analysis/analyzers/percolation_probability_analyzer.py
nexus/analysis/analyzers/spanning_cluster_size_analyzer.py
nexus/analysis/strategies/base_strategy.py
nexus/analysis/strategies/bond_strategy.py
nexus/analysis/strategies/coordination_strategy.py
nexus/analysis/strategies/distance_strategy.py
nexus/analysis/strategies/shared_strategy.py
nexus/analysis/strategies/search/__init__.py
nexus/analysis/strategies/search/neighbor_searcher.py
nexus/config/__init__.py
nexus/config/settings.py
nexus/core/__init__.py
nexus/core/cluster.py
nexus/core/frame.py
nexus/core/node.py
nexus/core/system.py
nexus/io/parser/__init__.py
nexus/io/parser/parser.py
nexus/io/reader/__init__.py
nexus/io/reader/base_reader.py
nexus/io/reader/lammps_reader.py
nexus/io/reader/reader_factory.py
nexus/io/reader/xyz_reader.py
nexus/io/writer/__init__.py
nexus/io/writer/base_writer.py
nexus/io/writer/clusters_writer.py
nexus/io/writer/logs_writer.py
nexus/io/writer/multiple_files_summary_writer.py
nexus/io/writer/performance_writer.py
nexus/io/writer/writer_factory.py
nexus/utils/__init__.py
nexus/utils/aesthetics.py
nexus/utils/geometry.py
nexus/utils/performance.py
nexus_cat-2.0.4.dist-info/licenses/LICENSE
nexus_cat-2.0.4.dist-info/METADATA
nexus_cat-2.0.4.dist-info/WHEEL
nexus_cat-2.0.4.dist-info/top_level.txt
nexus_cat-2.0.4.dist-info/RECORD
